{
    "consult_id": "p1nqku7vi2a9gj0",
    "user_id": "00955e13-05d5-46a9-bdef-9318bc8fada4",
    "consult_time": "2026-02-26",
    "consult_data": {
        "shape": {
            "total_questions": 10,
            "correct": 10,
            "incorrect": 0,
            "accuracy_percent": 100.0,
            "avg_reaction_time_s": 2.0618,
            "trial_log": [
                {
                    "question_num": 1,
                    "correct": true,
                    "reaction_time_s": 4.1555,
                    "patient_said_same": false,
                    "was_same": false
                },
                {
                    "question_num": 2,
                    "correct": true,
                    "reaction_time_s": 1.5769,
                    "patient_said_same": true,
                    "was_same": true
                },
                {
                    "question_num": 3,
                    "correct": true,
                    "reaction_time_s": 2.2036,
                    "patient_said_same": true,
                    "was_same": true
                },
                {
                    "question_num": 4,
                    "correct": true,
                    "reaction_time_s": 1.0197,
                    "patient_said_same": true,
                    "was_same": true
                },
                {
                    "question_num": 5,
                    "correct": true,
                    "reaction_time_s": 1.4021,
                    "patient_said_same": false,
                    "was_same": false
                },
                {
                    "question_num": 6,
                    "correct": true,
                    "reaction_time_s": 1.7387,
                    "patient_said_same": true,
                    "was_same": true
                },
                {
                    "question_num": 7,
                    "correct": true,
                    "reaction_time_s": 1.3057,
                    "patient_said_same": true,
                    "was_same": true
                },
                {
                    "question_num": 8,
                    "correct": true,
                    "reaction_time_s": 1.6499,
                    "patient_said_same": false,
                    "was_same": false
                },
                {
                    "question_num": 9,
                    "correct": true,
                    "reaction_time_s": 2.6588,
                    "patient_said_same": false,
                    "was_same": false
                },
                {
                    "question_num": 10,
                    "correct": true,
                    "reaction_time_s": 2.9074,
                    "patient_said_same": true,
                    "was_same": true
                }
            ]
        },
        "spiral": {
            "classification": 1,
            "prediction_value": 1.2382930630211106,
            "trace_file": "data/traces/b4e02551-25bb-4dba-8120-3716453b2a7e_spiral.csv",
            "augmented_features": {
                "x_pos": 9.4e-05,
                "y_pos": -0.054967,
                "time": 31.719903,
                "magnitude": 0.603759,
                "distance": 0.000413,
                "turns": 1.286199,
                "theta": 11.362547,
                "angular_velocity": 0.848894,
                "error": 0.005479
            },
            "n_points": 1768
        },
        "memory": {
            "score": 4,
            "total_trials": 8,
            "accuracy_percent": 50.0,
            "incorrect_count": 4,
            "avg_cell_distance": 1.0,
            "trial_log": [
                {
                    "trial_num": 1,
                    "icon_idx": 6,
                    "correct_cell": [
                        0,
                        2
                    ],
                    "clicked_cell": [
                        0,
                        3
                    ],
                    "correct": false,
                    "cell_distance": 1
                },
                {
                    "trial_num": 2,
                    "icon_idx": 1,
                    "correct_cell": [
                        1,
                        1
                    ],
                    "clicked_cell": [
                        1,
                        1
                    ],
                    "correct": true,
                    "cell_distance": 0
                },
                {
                    "trial_num": 3,
                    "icon_idx": 2,
                    "correct_cell": [
                        1,
                        3
                    ],
                    "clicked_cell": [
                        0,
                        0
                    ],
                    "correct": false,
                    "cell_distance": 4
                },
                {
                    "trial_num": 4,
                    "icon_idx": 0,
                    "correct_cell": [
                        1,
                        2
                    ],
                    "clicked_cell": [
                        1,
                        2
                    ],
                    "correct": true,
                    "cell_distance": 0
                },
                {
                    "trial_num": 5,
                    "icon_idx": 7,
                    "correct_cell": [
                        0,
                        3
                    ],
                    "clicked_cell": [
                        0,
                        1
                    ],
                    "correct": false,
                    "cell_distance": 2
                },
                {
                    "trial_num": 6,
                    "icon_idx": 5,
                    "correct_cell": [
                        0,
                        0
                    ],
                    "clicked_cell": [
                        0,
                        1
                    ],
                    "correct": false,
                    "cell_distance": 1
                },
                {
                    "trial_num": 7,
                    "icon_idx": 3,
                    "correct_cell": [
                        1,
                        0
                    ],
                    "clicked_cell": [
                        1,
                        0
                    ],
                    "correct": true,
                    "cell_distance": 0
                },
                {
                    "trial_num": 8,
                    "icon_idx": 4,
                    "correct_cell": [
                        0,
                        1
                    ],
                    "clicked_cell": [
                        0,
                        1
                    ],
                    "correct": true,
                    "cell_distance": 0
                }
            ]
        },
        "trail": {
            "completion_time": 10.85,
            "path_efficiency": 99.51,
            "path_smoothness": 63.57,
            "total_distance": 2694.56,
            "optimal_distance": 2681.36,
            "pause_count": 0,
            "total_pause_time": 0,
            "average_speed": 135.95,
            "speed_variability": 231.66,
            "errors": 0,
            "test_type": "A",
            "difficulty": "medium",
            "circle_path": [
                {
                    "circle": 1,
                    "timestamp_s": -0.0,
                    "x": 700,
                    "y": 459,
                    "input_method": "touchscreen"
                },
                {
                    "circle": 2,
                    "timestamp_s": 0.8103,
                    "x": 820,
                    "y": 278,
                    "input_method": "touchscreen"
                },
                {
                    "circle": 3,
                    "timestamp_s": 2.735,
                    "x": 483,
                    "y": 249,
                    "input_method": "touchscreen"
                },
                {
                    "circle": 4,
                    "timestamp_s": 4.2331,
                    "x": 363,
                    "y": 222,
                    "input_method": "touchscreen"
                },
                {
                    "circle": 5,
                    "timestamp_s": 5.3581,
                    "x": 279,
                    "y": 421,
                    "input_method": "touchscreen"
                },
                {
                    "circle": 6,
                    "timestamp_s": 5.9565,
                    "x": 340,
                    "y": 352,
                    "input_method": "touchscreen"
                },
                {
                    "circle": 7,
                    "timestamp_s": 6.8659,
                    "x": 144,
                    "y": 174,
                    "input_method": "touchscreen"
                },
                {
                    "circle": 8,
                    "timestamp_s": 7.7189,
                    "x": 122,
                    "y": 339,
                    "input_method": "touchscreen"
                },
                {
                    "circle": 9,
                    "timestamp_s": 9.8429,
                    "x": 891,
                    "y": 389,
                    "input_method": "touchscreen"
                },
                {
                    "circle": 10,
                    "timestamp_s": 10.8528,
                    "x": 918,
                    "y": 170,
                    "input_method": "touchscreen"
                }
            ]
        }
    }
}